[
    { "make": "BMW", "vin_model": "RS6", "og_model": "RS 6 (C5 4B) || RS 6 (C8 5G)", "status": "specify_or" },
    { "make": "BMW", "vin_model": "ActiveHybrid 3", "og_model": "3 Series", "status": "specify" },
    { "make": "BMW", "vin_model": "ActiveHybrid 5", "og_model": "5 Series", "status": "specify" },
    { "make": "BMW", "vin_model": "ActiveHybrid 7", "og_model": "7 Series", "status": "specify" },
    { "make": "BMW", "vin_model": "i3", "og_model": "i Series", "status": "specify" },
    { "make": "BMW", "vin_model": "i4", "og_model": "i Series", "status": "specify" },
    { "make": "BMW", "vin_model": "i7", "og_model": "i Series", "status": "specify" },
    { "make": "BMW", "vin_model": "i8", "og_model": "i Series", "status": "specify" },
    { "make": "BMW", "vin_model": "650i / B6", "og_model": "6 Series", "status": "specify" },
    { "make": "BMW", "vin_model": "750i / B7", "og_model": "7 Series", "status": "specify" },
    { "make": "Chevraolet", "vin_model": "Caprice Police Vehicle", "og_model": "N/A", "status": "remove" },
    { "make": "Ford", "vin_model": "Bronco Sport", "og_model": "Bronco", "status": "specify" },
    { "make": "Ford", "vin_model": "E-150", "og_model": "E-Series", "status": "specify" },
    { "make": "Ford", "vin_model": "E-250", "og_model": "E-Series", "status": "specify" },
    { "make": "Ford", "vin_model": "E-350", "og_model": "E-Series", "status": "specify" },
    { "make": "Ford", "vin_model": "F-150", "og_model": "F-150", "status": "specify" },
    { "make": "Ford", "vin_model": "F-250", "og_model": "F-250/350", "status": "specify" },
    { "make": "Ford", "vin_model": "F-350", "og_model": "F-250/350", "status": "specify" },
    { "make": "Ford", "vin_model": "F-450", "og_model": "F-250/350", "status": "specify" },
    { "make": "Ford", "vin_model": "F-550", "og_model": "F-250/350", "status": "specify" },
    { "make": "Ford", "vin_model": "F-600", "og_model": "F-250/350", "status": "specify" },
    { "make": "Ford", "vin_model": "F-650", "og_model": "F-250/350", "status": "specify" },
    { "make": "Ford", "vin_model": "F-Super Duty", "og_model": "F-250/350", "status": "specify" },
    { "make": "honda", "vin_model": "Accord Crosstour", "og_model": "Accord || Crosstour", "status": "specify_or" },
    { "make": "Lexus", "vin_model": "ES", "og_model": "ES-Series", "status": "specify" },
    { "make": "Mazda", "vin_model": "Mazda5", "og_model": "5", "status": "specify" },
    { "make": "Mercedes-Benz", "vin_model": "ML-Class", "og_model": "M Class", "status": "specify" },
    { "make": "Mercedes-Benz", "vin_model": "SLS-Class", "og_model": "SLC Class", "status": "specify" },
    { "make": "MINI", "vin_model": "Cooper Coupe", "og_model": "Coupe", "status": "specify" },
    { "make": "MINI", "vin_model": "Cooper Convertible", "og_model": "Cabrio", "status": "specify" },
    { "make": "Nissan", "vin_model": "NV", "og_model": "NV Serires", "status": "specify" },
    { "make": "Nissan", "vin_model": "Nissan Z", "og_model": "Z", "status": "specify" },
    { "make": "RAM", "vin_model": "ProMaster 1500", "og_model": "ProMaster", "status": "specify" },
    { "make": "RAM", "vin_model": "ProMaster 2500", "og_model": "ProMaster", "status": "specify" },
    { "make": "RAM", "vin_model": "ProMaster 3500", "og_model": "ProMaster", "status": "specify" },
    { "make": "Tesla", "vin_model": "Semi", "og_model": "N/A", "status": "remove" },
    { "make": "Toyota", "vin_model": "Prius Prime", "og_model": "Prius", "status": "specify" },
    { "make": "Toyota", "vin_model": "Prius Plug-in", "og_model": "Prius", "status": "specify" },
    { "make": "Toyota", "vin_model": "Camry Solara", "og_model": "Solara", "status": "specify" }
    ]